cockroachcore/__init__.py
cockroachcore/cards.py
cockroachcore/game.py
cockroach_core-0.0.2.dist-info/LICENSE
cockroach_core-0.0.2.dist-info/METADATA
cockroach_core-0.0.2.dist-info/WHEEL
cockroach_core-0.0.2.dist-info/top_level.txt
cockroach_core-0.0.2.dist-info/RECORD
