Metadata-Version: 2.1
Name: cockroach-core
Version: 0.0.2
Summary: UNKNOWN
Home-page: http://gitlab.com/cockroach-poker/cockroach-core
Author: Simon Redding
Author-email: s1m0n.r3dd1ng@gmail.com
License: GPL3
Platform: UNKNOWN
Classifier: Programming Language :: Python :: 3
Classifier: License :: OSI Approved :: GNU General Public License v3 (GPLv3)
Classifier: Operating System :: OS Independent
Requires-Python: >=3.6
